maaspower/__init__.py
maaspower/__main__.py
maaspower/_version.py
maaspower/maas_globals.py
maaspower/maasconfig.py
maaspower/webhook.py
maaspower/devices/__init__.py
maaspower/devices/cisco_ios_poe_switch.py
maaspower/devices/kasa_device.py
maaspower/devices/shell_cmd.py
maaspower/devices/smart_thing.py
maaspower/devices/web_device.py
maaspower/devices/web_ui.py
maaspower-1.0.0.dist-info/LICENSE
maaspower-1.0.0.dist-info/METADATA
maaspower-1.0.0.dist-info/WHEEL
maaspower-1.0.0.dist-info/entry_points.txt
maaspower-1.0.0.dist-info/top_level.txt
maaspower-1.0.0.dist-info/RECORD
