Metadata-Version: 2.1
Name: maaspower
Version: 1.0.0
Summary: Power control webhook server for Canonical's MAAS
Author-email: Giles Knap <gilesknap@gmail.com>
License: Apache License
Project-URL: GitHub, https://github.com/gilesknap/maaspower
Classifier: Development Status :: 3 - Alpha
Classifier: License :: OSI Approved :: Apache Software License
Classifier: Programming Language :: Python :: 3.10
Classifier: Programming Language :: Python :: 3.11
Classifier: Programming Language :: Python :: 3.12
Requires-Python: >=3.10
License-File: LICENSE
Requires-Dist: flask
Requires-Dist: flask-basicauth
Requires-Dist: typing-extensions
Requires-Dist: pysmartthings
Requires-Dist: apischema
Requires-Dist: typer
Requires-Dist: ruamel.yaml
Requires-Dist: jsonschema
Requires-Dist: importlib-resources
Requires-Dist: selenium
Requires-Dist: netmiko ==4.4.0
Requires-Dist: python-kasa >=0.4.0
Requires-Dist: types-requests
Provides-Extra: dev
Requires-Dist: copier ; extra == 'dev'
Requires-Dist: mypy ; extra == 'dev'
Requires-Dist: myst-parser ; extra == 'dev'
Requires-Dist: pipdeptree ; extra == 'dev'
Requires-Dist: pre-commit ; extra == 'dev'
Requires-Dist: pydata-sphinx-theme >=0.12 ; extra == 'dev'
Requires-Dist: pytest ; extra == 'dev'
Requires-Dist: pytest-cov ; extra == 'dev'
Requires-Dist: ruff ; extra == 'dev'
Requires-Dist: sphinx-autobuild ; extra == 'dev'
Requires-Dist: sphinx-copybutton ; extra == 'dev'
Requires-Dist: sphinx-design ; extra == 'dev'
Requires-Dist: tox-direct ; extra == 'dev'
Requires-Dist: mock ; extra == 'dev'
Requires-Dist: types-mock ; extra == 'dev'
